modeltrack/__init__.py
modeltrack/experiment.py
modeltrack/report.py
utils/__init__.py
utils/config.py
utils/logging.py
modeltrack-1.0.2.dist-info/AUTHORS.rst
modeltrack-1.0.2.dist-info/LICENSE.txt
modeltrack-1.0.2.dist-info/METADATA
modeltrack-1.0.2.dist-info/WHEEL
modeltrack-1.0.2.dist-info/entry_points.txt
modeltrack-1.0.2.dist-info/top_level.txt
modeltrack-1.0.2.dist-info/RECORD
