Metadata-Version: 2.1
Name: modeltrack
Version: 1.0.2
Summary: PyTorch model config and result tracker
Home-page: https://github.com/adam-vanegdom/modeltrack
Author: Adam VanEgdom
Author-email: adam.vanegdom@gmail.com
License: MIT
Platform: any
Classifier: Development Status :: 4 - Beta
Classifier: Programming Language :: Python
License-File: LICENSE.txt
License-File: AUTHORS.rst
Requires-Dist: torch (==1.9.0)
Requires-Dist: matplotlib (==3.4.2)
Requires-Dist: easydict (==1.9)
Requires-Dist: fpdf (==1.7.2)
Requires-Dist: importlib-metadata ; python_version < "3.8"
Provides-Extra: testing
Requires-Dist: setuptools ; extra == 'testing'
Requires-Dist: pytest ; extra == 'testing'
Requires-Dist: pytest-cov ; extra == 'testing'
